pylittleeegle/BCI.py
pylittleeegle/Database.py
pylittleeegle/InOut.py
pylittleeegle/__init__.py
pylittleeegle/utils.py
pylittleeegle-0.1.1.dist-info/licenses/LICENSE
pylittleeegle-0.1.1.dist-info/METADATA
pylittleeegle-0.1.1.dist-info/WHEEL
pylittleeegle-0.1.1.dist-info/top_level.txt
pylittleeegle-0.1.1.dist-info/RECORD
