Metadata-Version: 2.4
Name: pylittleeegle
Version: 0.1.1
Summary: Python package for FII BCI Corpus (NY format). A lightweight Eegle.jl port.
Author-email: Fahim Doumi <fahim.doumi.pro@gmail.com>, Marco Congedo <marcocongedo@gmail.com>
Project-URL: Homepage, https://github.com/FhmDmi/pyLittleEegle
Project-URL: Bug Tracker, https://github.com/FhmDmi/pyLittleEegle/issues
Classifier: Programming Language :: Python :: 3
Classifier: License :: OSI Approved :: BSD License
Classifier: Operating System :: OS Independent
Classifier: Topic :: Scientific/Engineering :: Bio-Informatics
Classifier: Intended Audience :: Science/Research
Requires-Python: >=3.10
License-File: LICENSE
Requires-Dist: numpy
Requires-Dist: pandas
Requires-Dist: scikit-learn
Requires-Dist: pyriemann
Requires-Dist: scipy
Requires-Dist: pyyaml
Dynamic: license-file
